CHANGES.txt
README.txt
buildout.cfg
header.txt
setup.py
src/haufe.testrunner.ui.egg-info/PKG-INFO
src/haufe.testrunner.ui.egg-info/SOURCES.txt
src/haufe.testrunner.ui.egg-info/dependency_links.txt
src/haufe.testrunner.ui.egg-info/entry_points.txt
src/haufe.testrunner.ui.egg-info/not-zip-safe
src/haufe.testrunner.ui.egg-info/requires.txt
src/haufe.testrunner.ui.egg-info/top_level.txt
src/haufe_testrunner_ui/__init__.py
src/haufe_testrunner_ui/app.py
src/haufe_testrunner_ui/configure.zcml
src/haufe_testrunner_ui/ftesting.zcml
src/haufe_testrunner_ui/testing.py
src/haufe_testrunner_ui/app_templates/index.pt
src/haufe_testrunner_ui/app_templates/master.pt
src/haufe_testrunner_ui/app_templates/showresultlog.pt
src/haufe_testrunner_ui/app_templates/showresults.pt
src/haufe_testrunner_ui/app_templates/showruns.pt
src/haufe_testrunner_ui/static/logo.gif
src/haufe_testrunner_ui/static/rss.gif
src/haufe_testrunner_ui/static/styles.css