Metadata-Version: 1.0
Name: haufe.testrunner.ui
Version: 0.1.4
Summary: Webfrontend for haufe.testrunner results
Home-page: UNKNOWN
Author: Andreas Jung
Author-email: andreas.jung@haufe.de
License: ZPL
Keywords: Grok testrunner Haufe webfrontend unittests Zope
Platform: UNKNOWN
